bethany_ds/__init__.py
bethany_ds/admin.py
bethany_ds/apps.py
bethany_ds/models.py
bethany_ds/urls.py
bethany_ds/views.py
bethany_ds/migrations/__init__.py
bethany_ds/static/bethany_ds/css/navbar.css
bethany_ds/static/bethany_ds/css/style.css
bethany_ds/static/bethany_ds/css/colors/default.css
bethany_ds/static/bethany_ds/js/main.js
bethany_ds/templates/bethany_ds/base.html
bethany_ds/templates/bethany_ds/footer.html
bethany_ds/templates/bethany_ds/header.html
django_bethany_ds-0.1.2.dist-info/LICENSE
django_bethany_ds-0.1.2.dist-info/METADATA
django_bethany_ds-0.1.2.dist-info/WHEEL
django_bethany_ds-0.1.2.dist-info/top_level.txt
django_bethany_ds-0.1.2.dist-info/RECORD
